HGNM/__init__.py
HGNM/modules/__init__.py
HGNM/modules/get_message_passing_base.py
HGNM/modules/abstract/AbstractBlock.py
HGNM/modules/abstract/AbstractGraphAssertions.py
HGNM/modules/abstract/AbstractInputEmbedding.py
HGNM/modules/abstract/AbstractMessagePassingBase.py
HGNM/modules/abstract/AbstractModules.py
HGNM/modules/abstract/AbstractStack.py
HGNM/modules/abstract/__init__.py
HGNM/modules/common/Embedding.py
HGNM/modules/common/LatentMLP.py
HGNM/modules/common/UtilityModules.py
HGNM/modules/common/__init__.py
HGNM/modules/common/hmpn_util.py
HGNM/modules/heterogeneous/HeterogeneousBlock.py
HGNM/modules/heterogeneous/HeterogeneousGraphAssertions.py
HGNM/modules/heterogeneous/HeterogeneousInputEmbedding.py
HGNM/modules/heterogeneous/HeterogeneousMessagePassingBase.py
HGNM/modules/heterogeneous/HeterogeneousModules.py
HGNM/modules/heterogeneous/HeterogeneousStack.py
HGNM/modules/heterogeneous/__init__.py
HGNM/modules/heterogeneous/mock/MockHeteroBase.py
HGNM/modules/heterogeneous/mock/__init__.py
HGNM/modules/homogeneous/HomogeneousBlock.py
HGNM/modules/homogeneous/HomogeneousGraphAssertions.py
HGNM/modules/homogeneous/HomogeneousInputEmbedding.py
HGNM/modules/homogeneous/HomogeneousMessagePassingBase.py
HGNM/modules/homogeneous/HomogeneousModules.py
HGNM/modules/homogeneous/HomogeneousStack.py
HGNM/modules/homogeneous/__init__.py
HGNM/util/Keys.py
HGNM/util/Types.py
HGNM/util/__init__.py
hgnm-0.0.2.dist-info/LICENSE
hgnm-0.0.2.dist-info/METADATA
hgnm-0.0.2.dist-info/WHEEL
hgnm-0.0.2.dist-info/top_level.txt
hgnm-0.0.2.dist-info/RECORD
